{
  "data_asset_type": null,
  "expectation_suite_name": "NewCust_expactation.demo",
  "expectations": [
    {
      "expectation_type": "expect_table_row_count_to_be_between",
      "kwargs": {
        "max_value": 1000,
        "min_value": 1000
      },
      "meta": {
        "profiler_details": {
          "metric_configuration": {
            "domain_kwargs": {},
            "metric_name": "table.row_count",
            "metric_value_kwargs": null
          },
          "num_batches": 1
        }
      }
    },
    {
      "expectation_type": "expect_table_columns_to_match_set",
      "kwargs": {
        "column_set": [
          "past_3_years_bike_related_purchases",
          "postcode",
          "last_name",
          "property_valuation",
          "job_title",
          "job_industry_category",
          "deceased_indicator",
          "Rank",
          "country",
          "gender",
          "Unnamed: 17",
          "owns_car",
          "Unnamed: 20",
          "Value",
          "Unnamed: 18",
          "DOB",
          "state",
          "tenure",
          "first_name",
          "wealth_segment",
          "address",
          "Unnamed: 19",
          "Unnamed: 16"
        ],
        "exact_match": null
      },
      "meta": {
        "profiler_details": {
          "success_ratio": 1.0
        }
      }
    }
  ],
  "ge_cloud_id": null,
  "meta": {
    "citations": [
      {
        "citation_date": "2023-02-12T19:48:58.680468Z",
        "comment": "Created by effective Rule-Based Profiler of OnboardingDataAssistant with the configuration included.\n"
      }
    ],
    "great_expectations_version": "0.15.48"
  }
}